python_artisan/__init__.py
python_artisan/main.py
python_artisan/services/__init__.py
python_artisan/services/application.py
python_artisan/services/handler.py
python_artisan/services/migrate.py
python_artisan/services/model.py
python_artisan/services/request.py
python_artisan/services/response.py
python_artisan/services/service.py
python_artisan/stubs/handler/alexa_skill_kit_subscribe.stub
python_artisan/stubs/handler/amazon_appsync_subsribe.stub
python_artisan/stubs/handler/amazon_kinesis_subscribe.stub
python_artisan/stubs/handler/amazon_lex_subscribe.stub
python_artisan/stubs/handler/amazon_mq_subscribe.stub
python_artisan/stubs/handler/amazon_msk_subscribe.stub
python_artisan/stubs/handler/amazon_redshift_subscribe.stub
python_artisan/stubs/handler/amazon_timestream_subscribe.stub
python_artisan/stubs/handler/api_subscribe.stub
python_artisan/stubs/handler/aws_codecommit_subscribe.stub
python_artisan/stubs/handler/aws_config_subscribe.stub
python_artisan/stubs/handler/aws_iot_button_subscribe.stub
python_artisan/stubs/handler/aws_iot_core_subscribe.stub
python_artisan/stubs/handler/aws_secrets_manager_rotation_subscribe.stub
python_artisan/stubs/handler/aws_step_function_subscribe.stub
python_artisan/stubs/handler/cloudtrail_subscribe.stub
python_artisan/stubs/handler/cloudwatch_logs_subscribe.stub
python_artisan/stubs/handler/cognito_subscribe.stub
python_artisan/stubs/handler/default.stub
python_artisan/stubs/handler/elastic_load_balancer_subscribe.stub
python_artisan/stubs/handler/mqtt_over_ws_subscribe.stub
python_artisan/stubs/handler/s3_subscribe.stub
python_artisan/stubs/handler/ses_subscribe.stub
python_artisan/stubs/handler/sns_subscribe.stub
python_artisan/stubs/handler/sqs_both.stub
python_artisan/stubs/handler/sqs_listen.stub
python_artisan/stubs/handler/sqs_publish.stub
python_artisan/stubs/handler/sqs_subscribe.stub
python_artisan/stubs/handler/sqs_trigger.stub
python_artisan/stubs/migration/mssql_alembic.stub
python_artisan-0.1.9.dist-info/entry_points.txt
python_artisan-0.1.9.dist-info/METADATA
python_artisan-0.1.9.dist-info/WHEEL
python_artisan-0.1.9.dist-info/RECORD
